mime_ext/__init__.py
mime_ext/core.py
mimetypes_extension-0.1.0.dist-info/LICENSE
mimetypes_extension-0.1.0.dist-info/METADATA
mimetypes_extension-0.1.0.dist-info/WHEEL
mimetypes_extension-0.1.0.dist-info/top_level.txt
mimetypes_extension-0.1.0.dist-info/RECORD
