Metadata-Version: 2.2
Name: mimetypes-extension
Version: 0.1.0
Summary: A Python package to get file extensions from MIME types, with support for additional formats.
Author-email: Sahil Alam <mail@alam.eu.org>
License: MIT License
Project-URL: Homepage, https://github.com/prono69/mimetypes-extension
Project-URL: Bug Reports, https://github.com/prono69/mimetypes-extension/issues
Project-URL: Source, https://github.com/prono69/mimetypes-extension
Keywords: mime,content-type,mapping,file extensions
Classifier: Programming Language :: Python :: 3
Classifier: License :: OSI Approved :: MIT License
Classifier: Operating System :: OS Independent
Requires-Python: >=3.7
License-File: LICENSE
